agentdiff_coordination/__init__.py
agentdiff_coordination/config.py
agentdiff_coordination/coordination.py
agentdiff_coordination/decorators.py
agentdiff_coordination/exceptions.py
agentdiff_coordination/logging.py
agentdiff_coordination/persistence/__init__.py
agentdiff_coordination/persistence/file_persistence.py
agentdiff_coordination/persistence/persistence_interface.py
agentdiff_coordination/persistence/redis_persistence.py
agentdiff_coordination/pubsub/__init__.py
agentdiff_coordination/pubsub/pubsub_broker.py
agentdiff_coordination/pubsub/pubsub_coordination.py
agentdiff_coordination-0.1.1.dist-info/METADATA
agentdiff_coordination-0.1.1.dist-info/WHEEL
agentdiff_coordination-0.1.1.dist-info/licenses/LICENSE
agentdiff_coordination-0.1.1.dist-info/RECORD
