Metadata-Version: 2.4
Name: agentdiff-coordination
Version: 0.1.1
Summary: Lightweight coordination library for AI agents to prevent concurrency issues
Project-URL: Homepage, https://github.com/AgentDiff/agentdiff-coordination
Project-URL: Repository, https://github.com/AgentDiff/agentdiff-coordination
Project-URL: Issues, https://github.com/AgentDiff/agentdiff-coordination/issues
Project-URL: Documentation, https://github.com/AgentDiff/agentdiff-coordination#readme
Author-email: AgentDiff Team <hello@agentdiff.com>
License-Expression: MIT
License-File: LICENSE
Keywords: agentdiff,agents,ai,concurrency,coordination,python,race-conditions
Classifier: Development Status :: 4 - Beta
Classifier: Intended Audience :: Developers
Classifier: License :: OSI Approved :: MIT License
Classifier: Programming Language :: Python :: 3
Classifier: Programming Language :: Python :: 3.9
Classifier: Programming Language :: Python :: 3.10
Classifier: Programming Language :: Python :: 3.11
Classifier: Programming Language :: Python :: 3.12
Classifier: Programming Language :: Python :: 3.13
Classifier: Topic :: Software Development :: Libraries :: Python Modules
Classifier: Topic :: System :: Distributed Computing
Requires-Python: >=3.9
Requires-Dist: wrapt>=1.16.0
Provides-Extra: dev
Requires-Dist: anthropic>=0.64.0; extra == 'dev'
Requires-Dist: crewai>=0.5.0; extra == 'dev'
Requires-Dist: openai>=1.99.9; extra == 'dev'
Requires-Dist: pytest-asyncio>=0.21.0; extra == 'dev'
Requires-Dist: pytest>=8.0.0; extra == 'dev'
Requires-Dist: python-dotenv>=1.1.1; extra == 'dev'
